stressanapi/CHANGELOG.md
stressanapi/README.md
stressanapi/example.json
stressanapi/simple_stressanapi_server.py
stressanapi/stressanapi.py
stressanapi/test_stressanapi.py
stressanapi-1.0.3.dist-info/LICENSE
stressanapi-1.0.3.dist-info/METADATA
stressanapi-1.0.3.dist-info/WHEEL
stressanapi-1.0.3.dist-info/entry_points.txt
stressanapi-1.0.3.dist-info/top_level.txt
stressanapi-1.0.3.dist-info/RECORD
